setup.py
django_s3_policy_sync.egg-info/PKG-INFO
django_s3_policy_sync.egg-info/SOURCES.txt
django_s3_policy_sync.egg-info/dependency_links.txt
django_s3_policy_sync.egg-info/not-zip-safe
django_s3_policy_sync.egg-info/requires.txt
django_s3_policy_sync.egg-info/top_level.txt
s3_policy_sync/__init__.py
s3_policy_sync/middleware.py