Metadata-Version: 1.0
Name: django-s3-policy-sync
Version: 0.2.0
Summary: Django middleware that synchronizes S3 policy to from files
Home-page: https://github.com/Rhumbix/django-s3-policy-sync.git
Author: Kenneth Jiang
Author-email: kenneth@rhumbix.com
License: MIT
Platform: UNKNOWN
